google_serp_api/__init__.py
google_serp_api/__version__.py
google_serp_api/client.py
google_serp_api/default_headers.py
google_serp_api-1.0.5.dist-info/LICENSE
google_serp_api-1.0.5.dist-info/METADATA
google_serp_api-1.0.5.dist-info/WHEEL
google_serp_api-1.0.5.dist-info/top_level.txt
google_serp_api-1.0.5.dist-info/RECORD
