Metadata-Version: 2.1
Name: google-serp-api
Version: 1.0.5
Summary: The Google SERP API provides real-time access to structured Google search results, offering no blocks or CAPTCHAs.
Home-page: https://github.com/HasData/google-serp-api-python
Author: Roman Milyushkevich
Author-email: roman@hasdata.com
Maintainer: Roman Milyushkevich
Maintainer-email: roman@hasdata.com
License: MIT
Platform: UNKNOWN
Classifier: License :: OSI Approved :: MIT License
Classifier: Programming Language :: Python
Classifier: Programming Language :: Python :: 3
Classifier: Programming Language :: Python :: 3.6
Classifier: Programming Language :: Python :: 3.7
Classifier: Programming Language :: Python :: 3.8
Classifier: Programming Language :: Python :: 3.9
Classifier: Programming Language :: Python :: 3.10
Classifier: Programming Language :: Python :: 3.11
Classifier: Programming Language :: Python :: 3.12
Classifier: Topic :: Software Development :: Libraries :: Python Modules
Requires-Python: >=3.6
License-File: LICENSE
